Workbook

Sheet Índice
B2: ÍNDICE DO ARQUIVO
B4: Nº | C4: Planilha | D4: Descrição
B5: 1 | C5: Renúncias Fiscais Sudam-Sudene | D5: Redução 75% Projeto Setor Prioritário e Redução Por Reinvestimento - Período 2015 a 2023 (11.310 registros)
B6: 2 | C6: IPCA_Fatores | D6: Fatores de correção IPCA por ano (2015-2023)
B7: 3 | C7: Resumo_por_Empresa | D7: Totais consolidados por empresa (2.247 empresas)
B9: Última atualização: 09/07/2026

Sheet Renúncias Fiscais Sudam-Sudene
A1: Ano-Calendário | B1: CNPJ | C1: Beneficiário | D1: Nome Fantasia | E1: UF | F1: Município | G1: CNAE | H1: Tipo de Renúncia | I1: Benefício Fiscal | J1: Valor Renunciado(R$) | K1: Valor Renunciado atualizado pelo IPCA até 31/05/2026 (R$)
A2: 2018 | B2: 11.844.663/0001-09 | C2: 1TELECOM SERVICOS DE TECNOLOGIA EM INTERNET LTDA | D2: 1TELECOM | E2: PERNAMBUCO | F2: RECIFE | G2: 61108 - Telecomunicações por fio | H2: Declarado pelo Contribuinte para Apuração do IRPJ e da CSLL | I2: Sudam/Sudene - Redução 75% Projeto Setor Prioritário | J2: 658675.67 | K2: =J2*_xlfn.XLOOKUP(A2,IPCA_Fatores!$A$2:$A$10,IPCA_Fatores!$C$2:$C$10) -> 986691.23
A3: 2019 | B3: 11.844.663/0001-09 | C3: 1TELECOM SERVICOS DE TECNOLOGIA EM INTERNET LTDA | D3: 1TELECOM | E3: PERNAMBUCO | F3: RECIFE | G3: 61108 - Telecomunicações por fio | H3: Declarado pelo Contribuinte para Apuração do IRPJ e da CSLL | I3: Sudam/Sudene - Redução 75% Projeto Setor Prioritário | J3: 251732.73 | K3: =J3*_xlfn.XLOOKUP(A3,IPCA_Fatores!$A$2:$A$10,IPCA_Fatores!$C$2:$C$10) -> 361512.56
A4: 2020 | B4: 11.844.663/0001-09 | C4: 1TELECOM SERVICOS DE TECNOLOGIA EM INTERNET LTDA | D4: 1TELECOM | E4: PERNAMBUCO | F4: RECIFE | G4: 61108 - Telecomunicações por fio | H4: Declarado pelo Contribuinte para Apuração do IRPJ e da CSLL | I4: Sudam/Sudene - Redução 75% Projeto Setor Prioritário | J4: 376707.82 | K4: =J4*_xlfn.XLOOKUP(A4,IPCA_Fatores!$A$2:$A$10,IPCA_Fatores!$C$2:$C$10) -> 517593.64
A5: 2021 | B5: 11.844.663/0001-09 | C5: 1TELECOM SERVICOS DE TECNOLOGIA EM INTERNET LTDA | D5: 1TELECOM | E5: PERNAMBUCO | F5: RECIFE | G5: 61108 - Telecomunicações por fio | H5: Declarado pelo Contribuinte para Apuração do IRPJ e da CSLL | I5: Sudam/Sudene - Redução 75% Projeto Setor Prioritário | J5: 348957.85 | K5: =J5*_xlfn.XLOOKUP(A5,IPCA_Fatores!$A$2:$A$10,IPCA_Fatores!$C$2:$C$10) -> 435640.01
A6: 2022 | B6: 11.844.663/0001-09 | C6: 1TELECOM SERVICOS DE TECNOLOGIA EM INTERNET LTDA | D6: 1TELECOM | E6: PERNAMBUCO | F6: RECIFE | G6: 61108 - Telecomunicações por fio | H6: Declarado pelo Contribuinte para Apuração do IRPJ e da CSLL | I6: Sudam/Sudene - Redução 75% Projeto Setor Prioritário | J6: 419468.24 | K6: =J6*_xlfn.XLOOKUP(A6,IPCA_Fatores!$A$2:$A$10,IPCA_Fatores!$C$2:$C$10) -> 495004.62
A7: 2023 | B7: 11.844.663/0001-09 | C7: 1TELECOM SERVICOS DE TECNOLOGIA EM INTERNET LTDA | D7: 1TELECOM | E7: PERNAMBUCO | F7: RECIFE | G7: 61108 - Telecomunicações por fio | H7: Declarado pelo Contribuinte para Apuração do IRPJ e da CSLL | I7: Sudam/Sudene - Redução 75% Projeto Setor Prioritário | J7: 2181220.8 | K7: =J7*_xlfn.XLOOKUP(A7,IPCA_Fatores!$A$2:$A$10,IPCA_Fatores!$C$2:$C$10) -> 2460339.8
A8: 2023 | B8: 42.762.204/0001-00 | C8: 2 J COMERCIAL LTDA | E8: ESPIRITO SANTO | F8: NOVA VENÉCIA | G8: 46371 - Comércio atacadista especializado em produtos alimentícios não especificados anteriormente | H8: Declarado pelo Contribuinte para Apuração do IRPJ e da CSLL | I8: Sudam/Sudene - Redução 75% Projeto Setor Prioritário | J8: 791713.05 | K8: =J8*_xlfn.XLOOKUP(A8,IPCA_Fatores!$A$2:$A$10,IPCA_Fatores!$C$2:$C$10) -> 893024.27
A9: 2023 | B9: 42.762.204/0001-00 | C9: 2 J COMERCIAL LTDA | E9: ESPIRITO SANTO | F9: NOVA VENÉCIA | G9: 46371 - Comércio atacadista especializado em produtos alimentícios não especificados anteriormente | H9: Declarado pelo Contribuinte para Apuração do IRPJ e da CSLL | I9: Sudam/Sudene - Redução por Reinvestimento | J9: 79171.31 | K9: =IFERROR(J9*VLOOKUP(A9,IPCA_Fatores!$A$2:$C$10,3,FALSE),J9) -> 89302.432
A10: 2018 | B10: 19.675.900/0001-67 | C10: 3CAFFI INDUSTRIA E COMERCIO DE CAPSULAS S.A | E10: MINAS GERAIS | F10: MONTES CLAROS | G10: 10813 - Torrefação e moagem de café | H10: Declarado pelo Contribuinte para Apuração do IRPJ e da CSLL | I10: Sudam/Sudene - Redução 75% Projeto Setor Prioritário | J10: 1563799.9 | K10: =J10*_xlfn.XLOOKUP(A10,IPCA_Fatores!$A$2:$A$10,IPCA_Fatores!$C$2:$C$10) -> 2342560.6
A11: 2018 | B11: 19.675.900/0001-67 | C11: 3CAFFI INDUSTRIA E COMERCIO DE CAPSULAS S.A | E11: MINAS GERAIS | F11: MONTES CLAROS | G11: 10813 - Torrefação e moagem de café | H11: Declarado pelo Contribuinte para Apuração do IRPJ e da CSLL | I11: Sudam/Sudene - Redução por Reinvestimento | J11: 94907.99 | K11: =IFERROR(J11*VLOOKUP(A11,IPCA_Fatores!$A$2:$C$10,3,FALSE),J11) -> 142171.46
A12: 2019 | B12: 19.675.900/0001-67 | C12: 3CAFFI INDUSTRIA E COMERCIO DE CAPSULAS S.A | E12: MINAS GERAIS | F12: MONTES CLAROS | G12: 10813 - Torrefação e moagem de café | H12: Declarado pelo Contribuinte para Apuração do IRPJ e da CSLL | I12: Sudam/Sudene - Redução 75% Projeto Setor Prioritário | J12: 2948345.1 | K12: =J12*_xlfn.XLOOKUP(A12,IPCA_Fatores!$A$2:$A$10,IPCA_Fatores!$C$2:$C$10) -> 4234108.9
A13: 2019 | B13: 19.675.900/0001-67 | C13: 3CAFFI INDUSTRIA E COMERCIO DE CAPSULAS S.A | E13: MINAS GERAIS | F13: MONTES CLAROS | G13: 10813 - Torrefação e moagem de café | H13: Declarado pelo Contribuinte para Apuração do IRPJ e da CSLL | I13: Sudam/Sudene - Redução por Reinvestimento | J13: 107493.67 | K13: =IFERROR(J13*VLOOKUP(A13,IPCA_Fatores!$A$2:$C$10,3,FALSE),J13) -> 154371.31
A14: 2020 | B14: 19.675.900/0001-67 | C14: 3CAFFI INDUSTRIA E COMERCIO DE CAPSULAS S.A | E14: MINAS GERAIS | F14: MONTES CLAROS | G14: 10813 - Torrefação e moagem de café | H14: Declarado pelo Contribuinte para Apuração do IRPJ e da CSLL | I14: Sudam/Sudene - Redução 75% Projeto Setor Prioritário | J14: 3262879.8 | K14: =J14*_xlfn.XLOOKUP(A14,IPCA_Fatores!$A$2:$A$10,IPCA_Fatores!$C$2:$C$10) -> 4483171.7
A15: 2020 | B15: 19.675.900/0001-67 | C15: 3CAFFI INDUSTRIA E COMERCIO DE CAPSULAS S.A | E15: MINAS GERAIS | F15: MONTES CLAROS | G15: 10813 - Torrefação e moagem de café | H15: Declarado pelo Contribuinte para Apuração do IRPJ e da CSLL | I15: Sudam/Sudene - Redução por Reinvestimento | J15: 196846.52 | K15: =IFERROR(J15*VLOOKUP(A15,IPCA_Fatores!$A$2:$C$10,3,FALSE),J15) -> 270465.6
A16: 2021 | B16: 19.675.900/0001-67 | C16: 3CAFFI INDUSTRIA E COMERCIO DE CAPSULAS S.A | E16: MINAS GERAIS | F16: MONTES CLAROS | G16: 10813 - Torrefação e moagem de café | H16: Declarado pelo Contribuinte para Apuração do IRPJ e da CSLL | I16: Sudam/Sudene - Redução 75% Projeto Setor Prioritário | J16: 4955151.4 | K16: =J16*_xlfn.XLOOKUP(A16,IPCA_Fatores!$A$2:$A$10,IPCA_Fatores!$C$2:$C$10) -> 6186025.7
A17: 2021 | B17: 19.675.900/0001-67 | C17: 3CAFFI INDUSTRIA E COMERCIO DE CAPSULAS S.A | E17: MINAS GERAIS | F17: MONTES CLAROS | G17: 10813 - Torrefação e moagem de café | H17: Declarado pelo Contribuinte para Apuração do IRPJ e da CSLL | I17: Sudam/Sudene - Redução por Reinvestimento | J17: 298389.08 | K17: =IFERROR(J17*VLOOKUP(A17,IPCA_Fatores!$A$2:$C$10,3,FALSE),J17) -> 372509.81
A18: 2022 | B18: 19.675.900/0001-67 | C18: 3CAFFI INDUSTRIA E COMERCIO DE CAPSULAS S.A | E18: MINAS GERAIS | F18: MONTES CLAROS | G18: 10813 - Torrefação e moagem de café | H18: Declarado pelo Contribuinte para Apuração do IRPJ e da CSLL | I18: Sudam/Sudene - Redução 75% Projeto Setor Prioritário | J18: 5871653.1 | K18: =J18*_xlfn.XLOOKUP(A18,IPCA_Fatores!$A$2:$A$10,IPCA_Fatores!$C$2:$C$10) -> 6929000
A19: 2022 | B19: 19.675.900/0001-67 | C19: 3CAFFI INDUSTRIA E COMERCIO DE CAPSULAS S.A | E19: MINAS GERAIS | F19: MONTES CLAROS | G19: 10813 - Torrefação e moagem de café | H19: Declarado pelo Contribuinte para Apuração do IRPJ e da CSLL | I19: Sudam/Sudene - Redução por Reinvestimento | J19: 353379.18 | K19: =IFERROR(J19*VLOOKUP(A19,IPCA_Fatores!$A$2:$C$10,3,FALSE),J19) -> 417014.48
A20: 2023 | B20: 19.675.900/0001-67 | C20: 3CAFFI INDUSTRIA E COMERCIO DE CAPSULAS S.A | E20: MINAS GERAIS | F20: MONTES CLAROS | G20: 10813 - Torrefação e moagem de café | H20: Declarado pelo Contribuinte para Apuração do IRPJ e da CSLL | I20: Sudam/Sudene - Redução 75% Projeto Setor Prioritário | J20: 8091011.3 | K20: =J20*_xlfn.XLOOKUP(A20,IPCA_Fatores!$A$2:$A$10,IPCA_Fatores!$C$2:$C$10) -> 9126374.1
A21: 2023 | B21: 19.675.900/0001-67 | C21: 3CAFFI INDUSTRIA E COMERCIO DE CAPSULAS S.A | E21: MINAS GERAIS | F21: MONTES CLAROS | G21: 10813 - Torrefação e moagem de café | H21: Declarado pelo Contribuinte para Apuração do IRPJ e da CSLL | I21: Sudam/Sudene - Redução por Reinvestimento | J21: 486540.69 | K21: =IFERROR(J21*VLOOKUP(A21,IPCA_Fatores!$A$2:$C$10,3,FALSE),J21) -> 548800.66
A22: 2015 | B22: 08.014.346/0001-50 | C22: 3M MANAUS INDUSTRIA DE PRODUTOS QUIMICOS LTDA | D22: 3M MANAUS | E22: AMAZONAS | F22: MANAUS | G22: 20991 - Fabricação de produtos químicos não especificados anteriormente | H22: Declarado pelo Contribuinte para Apuração do IRPJ e da CSLL | I22: Sudam/Sudene - Redução 75% Projeto Setor Prioritário | J22: 15579466 | K22: =J22*_xlfn.XLOOKUP(A22,IPCA_Fatores!$A$2:$A$10,IPCA_Fatores!$C$2:$C$10) -> 26495314
A23: 2015 | B23: 08.014.346/0001-50 | C23: 3M MANAUS INDUSTRIA DE PRODUTOS QUIMICOS LTDA | D23: 3M MANAUS | E23: AMAZONAS | F23: MANAUS | G23: 20991 - Fabricação de produtos químicos não especificados anteriormente | H23: Declarado pelo Contribuinte para Apuração do IRPJ e da CSLL | I23: Sudam/Sudene - Redução por Reinvestimento | J23: 935657.54 | K23: =IFERROR(J23*VLOOKUP(A23,IPCA_Fatores!$A$2:$C$10,3,FALSE),J23) -> 1591231.7
A24: 2016 | B24: 08.014.346/0001-50 | C24: 3M MANAUS INDUSTRIA DE PRODUTOS QUIMICOS LTDA | D24: 3M MANAUS | E24: AMAZONAS | F24: MANAUS | G24: 20991 - Fabricação de produtos químicos não especificados anteriormente | H24: Declarado pelo Contribuinte para Apuração do IRPJ e da CSLL | I24: Sudam/Sudene - Redução 75% Projeto Setor Prioritário | J24: 26578214 | K24: =J24*_xlfn.XLOOKUP(A24,IPCA_Fatores!$A$2:$A$10,IPCA_Fatores!$C$2:$C$10) -> 42525546
A25: 2016 | B25: 08.014.346/0001-50 | C25: 3M MANAUS INDUSTRIA DE PRODUTOS QUIMICOS LTDA | D25: 3M MANAUS | E25: AMAZONAS | F25: MANAUS | G25: 20991 - Fabricação de produtos químicos não especificados anteriormente | H25: Declarado pelo Contribuinte para Apuração do IRPJ e da CSLL | I25: Sudam/Sudene - Redução por Reinvestimento | J25: 1595725.7 | K25: =IFERROR(J25*VLOOKUP(A25,IPCA_Fatores!$A$2:$C$10,3,FALSE),J25) -> 2553185.3
A26: 2017 | B26: 08.014.346/0001-50 | C26: 3M MANAUS INDUSTRIA DE PRODUTOS QUIMICOS LTDA | D26: 3M MANAUS | E26: AMAZONAS | F26: MANAUS | G26: 20991 - Fabricação de produtos químicos não especificados anteriormente | H26: Declarado pelo Contribuinte para Apuração do IRPJ e da CSLL | I26: Sudam/Sudene - Redução 75% Projeto Setor Prioritário | J26: 38054482 | K26: =J26*_xlfn.XLOOKUP(A26,IPCA_Fatores!$A$2:$A$10,IPCA_Fatores!$C$2:$C$10) -> 59143030
A27: 2017 | B27: 08.014.346/0001-50 | C27: 3M MANAUS INDUSTRIA DE PRODUTOS QUIMICOS LTDA | D27: 3M MANAUS | E27: AMAZONAS | F27: MANAUS | G27: 20991 - Fabricação de produtos químicos não especificados anteriormente | H27: Declarado pelo Contribuinte para Apuração do IRPJ e da CSLL | I27: Sudam/Sudene - Redução por Reinvestimento | J27: 2284245.5 | K27: =IFERROR(J27*VLOOKUP(A27,IPCA_Fatores!$A$2:$C$10,3,FALSE),J27) -> 3550099.5
A28: 2018 | B28: 08.014.346/0001-50 | C28: 3M MANAUS INDUSTRIA DE PRODUTOS QUIMICOS LTDA | D28: 3M MANAUS | E28: AMAZONAS | F28: MANAUS | G28: 20991 - Fabricação de produtos químicos não especificados anteriormente | H28: Declarado pelo Contribuinte para Apuração do IRPJ e da CSLL | I28: Sudam/Sudene - Redução 75% Projeto Setor Prioritário | J28: 44338040 | K28: =J28*_xlfn.XLOOKUP(A28,IPCA_Fatores!$A$2:$A$10,IPCA_Fatores!$C$2:$C$10) -> 66418052
A29: 2018 | B29: 08.014.346/0001-50 | C29: 3M MANAUS INDUSTRIA DE PRODUTOS QUIMICOS LTDA | D29: 3M MANAUS | E29: AMAZONAS | F29: MANAUS | G29: 20991 - Fabricação de produtos químicos não especificados anteriormente | H29: Declarado pelo Contribuinte para Apuração do IRPJ e da CSLL | I29: Sudam/Sudene - Redução por Reinvestimento | J29: 2661323.7 | K29: =IFERROR(J29*VLOOKUP(A29,IPCA_Fatores!$A$2:$C$10,3,FALSE),J29) -> 3986643
A30: 2019 | B30: 08.014.346/0001-50 | C30: 3M MANAUS INDUSTRIA DE PRODUTOS QUIMICOS LTDA | D30: 3M MANAUS | E30: AMAZONAS | F30: MANAUS | G30: 20991 - Fabricação de produtos químicos não especificados anteriormente | H30: Declarado pelo Contribuinte para Apuração do IRPJ e da CSLL | I30: Sudam/Sudene - Redução 75% Projeto Setor Prioritário | J30: 47100887 | K30: =J30*_xlfn.XLOOKUP(A30,IPCA_Fatores!$A$2:$A$10,IPCA_Fatores!$C$2:$C$10) -> 67641430
A31: 2019 | B31: 08.014.346/0001-50 | C31: 3M MANAUS INDUSTRIA DE PRODUTOS QUIMICOS LTDA | D31: 3M MANAUS | E31: AMAZONAS | F31: MANAUS | G31: 20991 - Fabricação de produtos químicos não especificados anteriormente | H31: Declarado pelo Contribuinte para Apuração do IRPJ e da CSLL | I31: Sudam/Sudene - Redução por Reinvestimento | J31: 2644607.2 | K31: =IFERROR(J31*VLOOKUP(A31,IPCA_Fatores!$A$2:$C$10,3,FALSE),J31) -> 3797911.8
A32: 2020 | B32: 08.014.346/0001-50 | C32: 3M MANAUS INDUSTRIA DE PRODUTOS QUIMICOS LTDA | D32: 3M MANAUS | E32: AMAZONAS | F32: MANAUS | G32: 20991 - Fabricação de produtos químicos não especificados anteriormente | H32: Declarado pelo Contribuinte para Apuração do IRPJ e da CSLL | I32: Sudam/Sudene - Redução 75% Projeto Setor Prioritário | J32: 54492139 | K32: =J32*_xlfn.XLOOKUP(A32,IPCA_Fatores!$A$2:$A$10,IPCA_Fatores!$C$2:$C$10) -> 74871780
A33: 2020 | B33: 08.014.346/0001-50 | C33: 3M MANAUS INDUSTRIA DE PRODUTOS QUIMICOS LTDA | D33: 3M MANAUS | E33: AMAZONAS | F33: MANAUS | G33: 20991 - Fabricação de produtos químicos não especificados anteriormente | H33: Declarado pelo Contribuinte para Apuração do IRPJ e da CSLL | I33: Sudam/Sudene - Redução por Reinvestimento | J33: 3270539 | K33: =IFERROR(J33*VLOOKUP(A33,IPCA_Fatores!$A$2:$C$10,3,FALSE),J33) -> 4493695.4
A34: 2021 | B34: 08.014.346/0001-50 | C34: 3M MANAUS INDUSTRIA DE PRODUTOS QUIMICOS LTDA | D34: 3M MANAUS | E34: AMAZONAS | F34: MANAUS | G34: 20991 - Fabricação de produtos químicos não especificados anteriormente | H34: Declarado pelo Contribuinte para Apuração do IRPJ e da CSLL | I34: Sudam/Sudene - Redução 75% Projeto Setor Prioritário | J34: 51030560 | K34: =J34*_xlfn.XLOOKUP(A34,IPCA_Fatores!$A$2:$A$10,IPCA_Fatores!$C$2:$C$10) -> 63706703
A35: 2021 | B35: 08.014.346/0001-50 | C35: 3M MANAUS INDUSTRIA DE PRODUTOS QUIMICOS LTDA | D35: 3M MANAUS | E35: AMAZONAS | F35: MANAUS | G35: 20991 - Fabricação de produtos químicos não especificados anteriormente | H35: Declarado pelo Contribuinte para Apuração do IRPJ e da CSLL | I35: Sudam/Sudene - Redução por Reinvestimento | J35: 3062805.3 | K35: =IFERROR(J35*VLOOKUP(A35,IPCA_Fatores!$A$2:$C$10,3,FALSE),J35) -> 3823615.2
A36: 2022 | B36: 08.014.346/0001-50 | C36: 3M MANAUS INDUSTRIA DE PRODUTOS QUIMICOS LTDA | D36: 3M MANAUS | E36: AMAZONAS | F36: MANAUS | G36: 20991 - Fabricação de produtos químicos não especificados anteriormente | H36: Declarado pelo Contribuinte para Apuração do IRPJ e da CSLL | I36: Sudam/Sudene - Redução 75% Projeto Setor Prioritário | J36: 73867064 | K36: =J36*_xlfn.XLOOKUP(A36,IPCA_Fatores!$A$2:$A$10,IPCA_Fatores!$C$2:$C$10) -> 87168789
A37: 2022 | B37: 08.014.346/0001-50 | C37: 3M MANAUS INDUSTRIA DE PRODUTOS QUIMICOS LTDA | D37: 3M MANAUS | E37: AMAZONAS | F37: MANAUS | G37: 20991 - Fabricação de produtos químicos não especificados anteriormente | H37: Declarado pelo Contribuinte para Apuração do IRPJ e da CSLL | I37: Sudam/Sudene - Redução por Reinvestimento | J37: 4462963.2 | K37: =IFERROR(J37*VLOOKUP(A37,IPCA_Fatores!$A$2:$C$10,3,FALSE),J37) -> 5266638.1
A38: 2023 | B38: 08.014.346/0001-50 | C38: 3M MANAUS INDUSTRIA DE PRODUTOS QUIMICOS LTDA | D38: 3M MANAUS | E38: AMAZONAS | F38: MANAUS | G38: 20991 - Fabricação de produtos químicos não especificados anteriormente | H38: Declarado pelo Contribuinte para Apuração do IRPJ e da CSLL | I38: Sudam/Sudene - Redução 75% Projeto Setor Prioritário | J38: 80781988 | K38: =J38*_xlfn.XLOOKUP(A38,IPCA_Fatores!$A$2:$A$10,IPCA_Fatores!$C$2:$C$10) -> 91119221
A39: 2023 | B39: 08.014.346/0001-50 | C39: 3M MANAUS INDUSTRIA DE PRODUTOS QUIMICOS LTDA | D39: 3M MANAUS | E39: AMAZONAS | F39: MANAUS | G39: 20991 - Fabricação de produtos químicos não especificados anteriormente | H39: Declarado pelo Contribuinte para Apuração do IRPJ e da CSLL | I39: Sudam/Sudene - Redução por Reinvestimento | J39: 4848181.7 | K39: =IFERROR(J39*VLOOKUP(A39,IPCA_Fatores!$A$2:$C$10,3,FALSE),J39) -> 5468577.2
A40: 2023 | B40: 23.018.639/0001-08 | C40: 3R BAHIA S.A | E40: RIO DE JANEIRO | F40: RIO DE JANEIRO | G40: 06000 - Extração de petróleo e gás natural | H40: Declarado pelo Contribuinte para Apuração do IRPJ e da CSLL | I40: Sudam/Sudene - Redução 75% Projeto Setor Prioritário | J40: 821967.92 | K40: =J40*_xlfn.XLOOKUP(A40,IPCA_Fatores!$A$2:$A$10,IPCA_Fatores!$C$2:$C$10) -> 927150.69
A41: 2022 | B41: 33.443.860/0001-59 | C41: 3R MACAU S.A. | E41: RIO DE JANEIRO | F41: RIO DE JANEIRO | G41: 09106 - Atividades de apoio à extração de petróleo e gás natural | H41: Declarado pelo Contribuinte para Apuração do IRPJ e da CSLL | I41: Sudam/Sudene - Redução 75% Projeto Setor Prioritário | J41: 90263565 | K41: =J41*_xlfn.XLOOKUP(A41,IPCA_Fatores!$A$2:$A$10,IPCA_Fatores!$C$2:$C$10) -> 1.0651791e+08
A42: 2023 | B42: 33.443.860/0001-59 | C42: 3R MACAU S.A. | E42: RIO DE JANEIRO | F42: RIO DE JANEIRO | G42: 09106 - Atividades de apoio à extração de petróleo e gás natural | H42: Declarado pelo Contribuinte para Apuração do IRPJ e da CSLL | I42: Sudam/Sudene - Redução 75% Projeto Setor Prioritário | J42: 79431822 | K42: =J42*_xlfn.XLOOKUP(A42,IPCA_Fatores!$A$2:$A$10,IPCA_Fatores!$C$2:$C$10) -> 89596281
A43: 2023 | B43: 02.857.854/0001-14 | C43: 3R PETROLEUM OFFSHORE S.A. | E43: RIO DE JANEIRO | F43: RIO DE JANEIRO | G43: 06000 - Extração de petróleo e gás natural | H43: Declarado pelo Contribuinte para Apuração do IRPJ e da CSLL | I43: Sudam/Sudene - Redução 75% Projeto Setor Prioritário | J43: 6881767.9 | K43: =J43*_xlfn.XLOOKUP(A43,IPCA_Fatores!$A$2:$A$10,IPCA_Fatores!$C$2:$C$10) -> 7762390.3
A44: 2023 | B44: 02.857.854/0001-14 | C44: 3R PETROLEUM OFFSHORE S.A. | E44: RIO DE JANEIRO | F44: RIO DE JANEIRO | G44: 06000 - Extração de petróleo e gás natural | H44: Declarado pelo Contribuinte para Apuração do IRPJ e da CSLL | I44: Sudam/Sudene - Redução por Reinvestimento | J44: 413113.26 | K44: =IFERROR(J44*VLOOKUP(A44,IPCA_Fatores!$A$2:$C$10,3,FALSE),J44) -> 465977.12
A45: 2023 | B45: 44.186.763/0001-44 | C45: 3R POTIGUAR S.A. | E45: RIO DE JANEIRO | F45: RIO DE JANEIRO | G45: 19217 - Fabricação de produtos do refino de petróleo | H45: Declarado pelo Contribuinte para Apuração do IRPJ e da CSLL | I45: Sudam/Sudene - Redução 75% Projeto Setor Prioritário | J45: 7079130.4 | K45: =J45*_xlfn.XLOOKUP(A45,IPCA_Fatores!$A$2:$A$10,IPCA_Fatores!$C$2:$C$10) -> 7985008.3
A46: 2023 | B46: 44.186.763/0001-44 | C46: 3R POTIGUAR S.A. | E46: RIO DE JANEIRO | F46: RIO DE JANEIRO | G46: 19217 - Fabricação de produtos do refino de petróleo | H46: Declarado pelo Contribuinte para Apuração do IRPJ e da CSLL | I46: Sudam/Sudene - Redução por Reinvestimento | J46: 424955.93 | K46: =IFERROR(J46*VLOOKUP(A46,IPCA_Fatores!$A$2:$C$10,3,FALSE),J46) -> 479335.23
A47: 2022 | B47: 35.156.290/0001-41 | C47: 3R RIO VENTURA S.A. | E47: RIO DE JANEIRO | F47: RIO DE JANEIRO | G47: 06000 - Extração de petróleo e gás natural | H47: Declarado pelo Contribuinte para Apuração do IRPJ e da CSLL | I47: Sudam/Sudene - Redução 75% Projeto Setor Prioritário | J47: 7090628.8 | K47: =J47*_xlfn.XLOOKUP(A47,IPCA_Fatores!$A$2:$A$10,IPCA_Fatores!$C$2:$C$10) -> 8367484.6
A48: 2023 | B48: 35.156.290/0001-41 | C48: 3R RIO VENTURA S.A. | E48: RIO DE JANEIRO | F48: RIO DE JANEIRO | G48: 06000 - Extração de petróleo e gás natural | H48: Declarado pelo Contribuinte para Apuração do IRPJ e da CSLL | I48: Sudam/Sudene - Redução 75% Projeto Setor Prioritário | J48: 15843125 | K48: =J48*_xlfn.XLOOKUP(A48,IPCA_Fatores!$A$2:$A$10,IPCA_Fatores!$C$2:$C$10) -> 17870483
A49: 2022 | B49: 52.127.214/0001-27 | C49: 3R RNCE S.A. | E49: RIO DE JANEIRO | F49: RIO DE JANEIRO | G49: 06000 - Extração de petróleo e gás natural | H49: Declarado pelo Contribuinte para Apuração do IRPJ e da CSLL | I49: Sudam/Sudene - Redução 75% Projeto Setor Prioritário | J49: 3783293.9 | K49: =J49*_xlfn.XLOOKUP(A49,IPCA_Fatores!$A$2:$A$10,IPCA_Fatores!$C$2:$C$10) -> 4464576.3
A50: 2023 | B50: 52.127.214/0001-27 | C50: 3R RNCE S.A. | E50: RIO DE JANEIRO | F50: RIO DE JANEIRO | G50: 06000 - Extração de petróleo e gás natural | H50: Declarado pelo Contribuinte para Apuração do IRPJ e da CSLL | I50: Sudam/Sudene - Redução 75% Projeto Setor Prioritário | J50: 3734509.2 | K50: =J50*_xlfn.XLOOKUP(A50,IPCA_Fatores!$A$2:$A$10,IPCA_Fatores!$C$2:$C$10) -> 4212394.1
A51: 2017 | B51: 04.497.756/0001-49 | C51: A ALVES DE SOUSA INDUSTRIA E COMERCIO DE MOTOS LTDA | D51: AUTO PECAS SOUSA | E51: AMAZONAS | F51: MANAUS | G51: 00000 - Sem informação | H51: Declarado pelo Contribuinte para Apuração do IRPJ e da CSLL | I51: Sudam/Sudene - Redução 75% Projeto Setor Prioritário | J51: 364648.45 | K51: =J51*_xlfn.XLOOKUP(A51,IPCA_Fatores!$A$2:$A$10,IPCA_Fatores!$C$2:$C$10) -> 566724.67
A52: 2020 | B52: 04.497.756/0001-49 | C52: A ALVES DE SOUSA INDUSTRIA E COMERCIO DE MOTOS LTDA | D52: AUTO PECAS SOUSA | E52: AMAZONAS | F52: MANAUS | G52: 00000 - Sem informação | H52: Declarado pelo Contribuinte para Apuração do IRPJ e da CSLL | I52: Sudam/Sudene - Redução 75% Projeto Setor Prioritário | J52: 991903.49 | K52: =J52*_xlfn.XLOOKUP(A52,IPCA_Fatores!$A$2:$A$10,IPCA_Fatores!$C$2:$C$10) -> 1362867.8
A53: 2021 | B53: 04.497.756/0001-49 | C53: A ALVES DE SOUSA INDUSTRIA E COMERCIO DE MOTOS LTDA | D53: AUTO PECAS SOUSA | E53: AMAZONAS | F53: MANAUS | G53: 00000 - Sem informação | H53: Declarado pelo Contribuinte para Apuração do IRPJ e da CSLL | I53: Sudam/Sudene - Redução 75% Projeto Setor Prioritário | J53: 355899.29 | K53: =J53*_xlfn.XLOOKUP(A53,IPCA_Fatores!$A$2:$A$10,IPCA_Fatores!$C$2:$C$10) -> 444305.73
A54: 2022 | B54: 04.497.756/0001-49 | C54: A ALVES DE SOUSA INDUSTRIA E COMERCIO DE MOTOS LTDA | D54: AUTO PECAS SOUSA | E54: AMAZONAS | F54: MANAUS | G54: 00000 - Sem informação | H54: Declarado pelo Contribuinte para Apuração do IRPJ e da CSLL | I54: Sudam/Sudene - Redução 75% Projeto Setor Prioritário | J54: 2437111.3 | K54: =J54*_xlfn.XLOOKUP(A54,IPCA_Fatores!$A$2:$A$10,IPCA_Fatores!$C$2:$C$10) -> 2875977.8
A55: 2023 | B55: 04.497.756/0001-49 | C55: A ALVES DE SOUSA INDUSTRIA E COMERCIO DE MOTOS LTDA | D55: AUTO PECAS SOUSA | E55: AMAZONAS | F55: MANAUS | G55: 00000 - Sem informação | H55: Declarado pelo Contribuinte para Apuração do IRPJ e da CSLL | I55: Sudam/Sudene - Redução 75% Projeto Setor Prioritário | J55: 2140118 | K55: =J55*_xlfn.XLOOKUP(A55,IPCA_Fatores!$A$2:$A$10,IPCA_Fatores!$C$2:$C$10) -> 2413977.3
A56: 2015 | B56: 08.690.448/0001-96 | C56: A G HOTEIS E TURISMO S/A | E56: RIO GRANDE DO NORTE | F56: NATAL | G56: 55108 - Hotéis e similares | H56: Declarado pelo Contribuinte para Apuração do IRPJ e da CSLL | I56: Sudam/Sudene - Redução 75% Projeto Setor Prioritário | J56: 995161.03 | K56: =J56*_xlfn.XLOOKUP(A56,IPCA_Fatores!$A$2:$A$10,IPCA_Fatores!$C$2:$C$10) -> 1692426.7
A57: 2016 | B57: 08.690.448/0001-96 | C57: A G HOTEIS E TURISMO S/A | E57: RIO GRANDE DO NORTE | F57: NATAL | G57: 55108 - Hotéis e similares | H57: Declarado pelo Contribuinte para Apuração do IRPJ e da CSLL | I57: Sudam/Sudene - Redução 75% Projeto Setor Prioritário | J57: 617295.43 | K57: =J57*_xlfn.XLOOKUP(A57,IPCA_Fatores!$A$2:$A$10,IPCA_Fatores!$C$2:$C$10) -> 987682.05
A58: 2017 | B58: 08.690.448/0001-96 | C58: A G HOTEIS E TURISMO S/A | E58: RIO GRANDE DO NORTE | F58: NATAL | G58: 55108 - Hotéis e similares | H58: Declarado pelo Contribuinte para Apuração do IRPJ e da CSLL | I58: Sudam/Sudene - Redução 75% Projeto Setor Prioritário | J58: 215820.59 | K58: =J58*_xlfn.XLOOKUP(A58,IPCA_Fatores!$A$2:$A$10,IPCA_Fatores!$C$2:$C$10) -> 335421.29
A59: 2018 | B59: 08.690.448/0001-96 | C59: A G HOTEIS E TURISMO S/A | E59: RIO GRANDE DO NORTE | F59: NATAL | G59: 55108 - Hotéis e similares | H59: Declarado pelo Contribuinte para Apuração do IRPJ e da CSLL | I59: Sudam/Sudene - Redução 75% Projeto Setor Prioritário | J59: 96418.87 | K59: =J59*_xlfn.XLOOKUP(A59,IPCA_Fatores!$A$2:$A$10,IPCA_Fatores!$C$2:$C$10) -> 144434.75
A60: 2021 | B60: 08.690.448/0001-96 | C60: A G HOTEIS E TURISMO S/A | E60: RIO GRANDE DO NORTE | F60: NATAL | G60: 55108 - Hotéis e similares | H60: Declarado pelo Contribuinte para Apuração do IRPJ e da CSLL | I60: Sudam/Sudene - Redução 75% Projeto Setor Prioritário | J60: 3261196.7 | K60: =J60*_xlfn.XLOOKUP(A60,IPCA_Fatores!$A$2:$A$10,IPCA_Fatores!$C$2:$C$10) -> 4071287.6
A61: 2022 | B61: 08.690.448/0001-96 | C61: A G HOTEIS E TURISMO S/A | E61: RIO GRANDE DO NORTE | F61: NATAL | G61: 55108 - Hotéis e similares | H61: Declarado pelo Contribuinte para Apuração do IRPJ e da CSLL | I61: Sudam/Sudene - Redução 75% Projeto Setor Prioritário | J61: 2380704 | K61: =J61*_xlfn.XLOOKUP(A61,IPCA_Fatores!$A$2:$A$10,IPCA_Fatores!$C$2:$C$10) -> 2809412.9
A62: 2023 | B62: 07.473.964/0001-04 | C62: A T S - TERCEIRIZACAO DE MAO DE OBRA LTDA | D62: A T S | E62: SÃO PAULO | F62: SÃO PAULO | G62: 81117 - Serviços combinados para apoio a edifícios, exceto condomínios prediais | H62: Declarado pelo Contribuinte para Apuração do IRPJ e da CSLL | I62: Sudam/Sudene - Redução por Reinvestimento | J62: 673582.76 | K62: =IFERROR(J62*VLOOKUP(A62,IPCA_Fatores!$A$2:$C$10,3,FALSE),J62) -> 759777.49
A63: 2023 | B63: 08.145.915/0001-05 | C63: A&R DO BRASIL ACESSORIOS AUTOMOTIVOS LTDA | E63: PARAÍBA | F63: JOÃO PESSOA | G63: 29492 - Fabricação de peças e acessórios para veículos automotores não especificados anteriormente | H63: Declarado pelo Contribuinte para Apuração do IRPJ e da CSLL | I63: Sudam/Sudene - Redução 75% Projeto Setor Prioritário | J63: 752357.27 | K63: =J63*_xlfn.XLOOKUP(A63,IPCA_Fatores!$A$2:$A$10,IPCA_Fatores!$C$2:$C$10) -> 848632.34
A64: 2015 | B64: 07.656.227/0001-39 | C64: A. W. FABER-CASTELL AMAZONIA S. A. | E64: AMAZONAS | F64: MANAUS | G64: 32990 - Fabricação de produtos diversos não especificados anteriormente | H64: Declarado pelo Contribuinte para Apuração do IRPJ e da CSLL | I64: Sudam/Sudene - Redução 75% Projeto Setor Prioritário | J64: 3881555.4 | K64: =J64*_xlfn.XLOOKUP(A64,IPCA_Fatores!$A$2:$A$10,IPCA_Fatores!$C$2:$C$10) -> 6601191
A65: 2016 | B65: 07.656.227/0001-39 | C65: A. W. FABER-CASTELL AMAZONIA S. A. | E65: AMAZONAS | F65: MANAUS | G65: 32990 - Fabricação de produtos diversos não especificados anteriormente | H65: Declarado pelo Contribuinte para Apuração do IRPJ e da CSLL | I65: Sudam/Sudene - Redução 75% Projeto Setor Prioritário | J65: 4818846.7 | K65: =J65*_xlfn.XLOOKUP(A65,IPCA_Fatores!$A$2:$A$10,IPCA_Fatores!$C$2:$C$10) -> 7710227.9
A66: 2017 | B66: 07.656.227/0001-39 | C66: A. W. FABER-CASTELL AMAZONIA S. A. | E66: AMAZONAS | F66: MANAUS | G66: 32990 - Fabricação de produtos diversos não especificados anteriormente | H66: Declarado pelo Contribuinte para Apuração do IRPJ e da CSLL | I66: Sudam/Sudene - Redução 75% Projeto Setor Prioritário | J66: 4843352 | K66: =J66*_xlfn.XLOOKUP(A66,IPCA_Fatores!$A$2:$A$10,IPCA_Fatores!$C$2:$C$10) -> 7527379
A67: 2018 | B67: 07.656.227/0001-39 | C67: A. W. FABER-CASTELL AMAZONIA S. A. | E67: AMAZONAS | F67: MANAUS | G67: 32990 - Fabricação de produtos diversos não especificados anteriormente | H67: Declarado pelo Contribuinte para Apuração do IRPJ e da CSLL | I67: Sudam/Sudene - Redução 75% Projeto Setor Prioritário | J67: 6273964.6 | K67: =J67*_xlfn.XLOOKUP(A67,IPCA_Fatores!$A$2:$A$10,IPCA_Fatores!$C$2:$C$10) -> 9398352
A68: 2019 | B68: 07.656.227/0001-39 | C68: A. W. FABER-CASTELL AMAZONIA S. A. | E68: AMAZONAS | F68: MANAUS | G68: 32990 - Fabricação de produtos diversos não especificados anteriormente | H68: Declarado pelo Contribuinte para Apuração do IRPJ e da CSLL | I68: Sudam/Sudene - Redução 75% Projeto Setor Prioritário | J68: 4976093.5 | K68: =J68*_xlfn.XLOOKUP(A68,IPCA_Fatores!$A$2:$A$10,IPCA_Fatores!$C$2:$C$10) -> 7146151.6
A69: 2019 | B69: 30.746.945/0001-18 | C69: A.C.P. INDUSTRIA DE MOVEIS LTDA | E69: ESPIRITO SANTO | F69: LINHARES | G69: 31012 - Fabricação de móveis com predominância de madeira | H69: Declarado pelo Contribuinte para Apuração do IRPJ e da CSLL | I69: Sudam/Sudene - Redução 75% Projeto Setor Prioritário | J69: 320006.69 | K69: =J69*_xlfn.XLOOKUP(A69,IPCA_Fatores!$A$2:$A$10,IPCA_Fatores!$C$2:$C$10) -> 459560.57
A70: 2020 | B70: 30.746.945/0001-18 | C70: A.C.P. INDUSTRIA DE MOVEIS LTDA | E70: ESPIRITO SANTO | F70: LINHARES | G70: 31012 - Fabricação de móveis com predominância de madeira | H70: Declarado pelo Contribuinte para Apuração do IRPJ e da CSLL | I70: Sudam/Sudene - Redução 75% Projeto Setor Prioritário | J70: 993022.76 | K70: =J70*_xlfn.XLOOKUP(A70,IPCA_Fatores!$A$2:$A$10,IPCA_Fatores!$C$2:$C$10) -> 1364405.6
A71: 2021 | B71: 30.746.945/0001-18 | C71: A.C.P. INDUSTRIA DE MOVEIS LTDA | E71: ESPIRITO SANTO | F71: LINHARES | G71: 31012 - Fabricação de móveis com predominância de madeira | H71: Declarado pelo Contribuinte para Apuração do IRPJ e da CSLL | I71: Sudam/Sudene - Redução 75% Projeto Setor Prioritário | J71: 336319.99 | K71: =J71*_xlfn.XLOOKUP(A71,IPCA_Fatores!$A$2:$A$10,IPCA_Fatores!$C$2:$C$10) -> 419862.87
A72: 2022 | B72: 30.746.945/0001-18 | C72: A.C.P. INDUSTRIA DE MOVEIS LTDA | E72: ESPIRITO SANTO | F72: LINHARES | G72: 31012 - Fabricação de móveis com predominância de madeira | H72: Declarado pelo Contribuinte para Apuração do IRPJ e da CSLL | I72: Sudam/Sudene - Redução 75% Projeto Setor Prioritário | J72: 741735.41 | K72: =J72*_xlfn.XLOOKUP(A72,IPCA_Fatores!$A$2:$A$10,IPCA_Fatores!$C$2:$C$10) -> 875304.55
A73: 2022 | B73: 30.746.945/0001-18 | C73: A.C.P. INDUSTRIA DE MOVEIS LTDA | E73: ESPIRITO SANTO | F73: LINHARES | G73: 31012 - Fabricação de móveis com predominância de madeira | H73: Declarado pelo Contribuinte para Apuração do IRPJ e da CSLL | I73: Sudam/Sudene - Redução por Reinvestimento | J73: 20799.54 | K73: =IFERROR(J73*VLOOKUP(A73,IPCA_Fatores!$A$2:$C$10,3,FALSE),J73) -> 24545.049
A74: 2023 | B74: 30.746.945/0001-18 | C74: A.C.P. INDUSTRIA DE MOVEIS LTDA | E74: ESPIRITO SANTO | F74: LINHARES | G74: 31012 - Fabricação de móveis com predominância de madeira | H74: Declarado pelo Contribuinte para Apuração do IRPJ e da CSLL | I74: Sudam/Sudene - Redução 75% Projeto Setor Prioritário | J74: 625230.47 | K74: =J74*_xlfn.XLOOKUP(A74,IPCA_Fatores!$A$2:$A$10,IPCA_Fatores!$C$2:$C$10) -> 705237.82
A75: 2023 | B75: 30.746.945/0001-18 | C75: A.C.P. INDUSTRIA DE MOVEIS LTDA | E75: ESPIRITO SANTO | F75: LINHARES | G75: 31012 - Fabricação de móveis com predominância de madeira | H75: Declarado pelo Contribuinte para Apuração do IRPJ e da CSLL | I75: Sudam/Sudene - Redução por Reinvestimento | J75: 3724.81 | K75: =IFERROR(J75*VLOOKUP(A75,IPCA_Fatores!$A$2:$C$10,3,FALSE),J75) -> 4201.4537
A76: 2022 | B76: 29.112.864/0001-87 | C76: A.D. MAIA INDUSTRIA DE MOVEIS E COLCHOES LTDA | D76: COLCHOES AIAM | E76: PARAÍBA | F76: BAYEUX | G76: 31039 - Fabricação de móveis de outros materiais, exceto madeira e metal | H76: Declarado pelo Contribuinte para Apuração do IRPJ e da CSLL | I76: Sudam/Sudene - Redução 75% Projeto Setor Prioritário | J76: 90121.72 | K76: =J76*_xlfn.XLOOKUP(A76,IPCA_Fatores!$A$2:$A$10,IPCA_Fatores!$C$2:$C$10) -> 106350.53
A77: 2023 | B77: 29.112.864/0001-87 | C77: A.D. MAIA INDUSTRIA DE MOVEIS E COLCHOES LTDA | D77: COLCHOES AIAM | E77: PARAÍBA | F77: BAYEUX | G77: 31039 - Fabricação de móveis de outros materiais, exceto madeira e metal | H77: Declarado pelo Contribuinte para Apuração do IRPJ e da CSLL | I77: Sudam/Sudene - Redução 75% Projeto Setor Prioritário | J77: 52780.67 | K77: =J77*_xlfn.XLOOKUP(A77,IPCA_Fatores!$A$2:$A$10,IPCA_Fatores!$C$2:$C$10) -> 59534.726
A78: 2021 | B78: 26.662.449/0001-09 | C78: A.S PRODUTORA DE PROTEINA VEGETAL DO TOCANTINS LTDA | D78: NUTRITINS AGRO | E78: TOCANTINS | F78: PARAÍSO DO TOCANTINS | G78: 10660 - Fabricação de alimentos para animais | H78: Declarado pelo Contribuinte para Apuração do IRPJ e da CSLL | I78: Sudam/Sudene - Redução 75% Projeto Setor Prioritário | J78: 456475.88 | K78: =J78*_xlfn.XLOOKUP(A78,IPCA_Fatores!$A$2:$A$10,IPCA_Fatores!$C$2:$C$10) -> 569865.84
A79: 2020 | B79: 03.884.180/0001-00 | C79: AARON INDUSTRIA DE ROTULOS E ETIQUETAS ADESIVAS LTDA | D79: AARON | E79: CEARÁ | F79: EUSÉBIO | G79: 17419 - Fabricação de produtos de papel, cartolina, papel-cartão e papelão ondulado para uso comercial e de escritório | H79: Declarado pelo Contribuinte para Apuração do IRPJ e da CSLL | I79: Sudam/Sudene - Redução 75% Projeto Setor Prioritário | J79: 28704.71 | K79: =J79*_xlfn.XLOOKUP(A79,IPCA_Fatores!$A$2:$A$10,IPCA_Fatores!$C$2:$C$10) -> 39440.05
A80: 2021 | B80: 03.884.180/0001-00 | C80: AARON INDUSTRIA DE ROTULOS E ETIQUETAS ADESIVAS LTDA | D80: AARON | E80: CEARÁ | F80: EUSÉBIO | G80: 17419 - Fabricação de produtos de papel, cartolina, papel-cartão e papelão ondulado para uso comercial e de escritório | H80: Declarado pelo Contribuinte para Apuração do IRPJ e da CSLL | I80: Sudam/Sudene - Redução 75% Projeto Setor Prioritário | J80: 327568 | K80: =J80*_xlfn.XLOOKUP(A80,IPCA_Fatores!$A$2:$A$10,IPCA_Fatores!$C$2:$C$10) -> 408936.86
A81: 2022 | B81: 03.884.180/0001-00 | C81: AARON INDUSTRIA DE ROTULOS E ETIQUETAS ADESIVAS LTDA | D81: AARON | E81: CEARÁ | F81: EUSÉBIO | G81: 17419 - Fabricação de produtos de papel, cartolina, papel-cartão e papelão ondulado para uso comercial e de escritório | H81: Declarado pelo Contribuinte para Apuração do IRPJ e da CSLL | I81: Sudam/Sudene - Redução 75% Projeto Setor Prioritário | J81: 422140.66 | K81: =J81*_xlfn.XLOOKUP(A81,IPCA_Fatores!$A$2:$A$10,IPCA_Fatores!$C$2:$C$10) -> 498158.28
A82: 2023 | B82: 03.884.180/0001-00 | C82: AARON INDUSTRIA DE ROTULOS E ETIQUETAS ADESIVAS LTDA | D82: AARON | E82: CEARÁ | F82: EUSÉBIO | G82: 17419 - Fabricação de produtos de papel, cartolina, papel-cartão e papelão ondulado para uso comercial e de escritório | H82: Declarado pelo Contribuinte para Apuração do IRPJ e da CSLL | I82: Sudam/Sudene - Redução 75% Projeto Setor Prioritário | J82: 645990.5 | K82: =J82*_xlfn.XLOOKUP(A82,IPCA_Fatores!$A$2:$A$10,IPCA_Fatores!$C$2:$C$10) -> 728654.39
A83: 2023 | B83: 03.884.180/0001-00 | C83: AARON INDUSTRIA DE ROTULOS E ETIQUETAS ADESIVAS LTDA | D83: AARON | E83: CEARÁ | F83: EUSÉBIO | G83: 17419 - Fabricação de produtos de papel, cartolina, papel-cartão e papelão ondulado para uso comercial e de escritório | H83: Declarado pelo Contribuinte para Apuração do IRPJ e da CSLL | I83: Sudam/Sudene - Redução por Reinvestimento | J83: 39619.42 | K83: =IFERROR(J83*VLOOKUP(A83,IPCA_Fatores!$A$2:$C$10,3,FALSE),J83) -> 44689.302
A84: 2015 | B84: 37.432.689/0001-33 | C84: ABACO TECNOLOGIA DE INFORMACAO LTDA | D84: ABACO TECNOLOGIA DE INFORMACAO | E84: MATO GROSSO | F84: CUIABÁ | G84: 62023 - Desenvolvimento e licenciamento de programas de computador customizáveis | H84: Declarado pelo Contribuinte para Apuração do IRPJ e da CSLL | I84: Sudam/Sudene - Redução 75% Projeto Setor Prioritário | J84: 1202467.3 | K84: =J84*_xlfn.XLOOKUP(A84,IPCA_Fatores!$A$2:$A$10,IPCA_Fatores!$C$2:$C$10) -> 2044983.4
A85: 2016 | B85: 37.432.689/0001-33 | C85: ABACO TECNOLOGIA DE INFORMACAO LTDA | D85: ABACO TECNOLOGIA DE INFORMACAO | E85: MATO GROSSO | F85: CUIABÁ | G85: 62023 - Desenvolvimento e licenciamento de programas de computador customizáveis | H85: Declarado pelo Contribuinte para Apuração do IRPJ e da CSLL | I85: Sudam/Sudene - Redução 75% Projeto Setor Prioritário | J85: 929008.92 | K85: =J85*_xlfn.XLOOKUP(A85,IPCA_Fatores!$A$2:$A$10,IPCA_Fatores!$C$2:$C$10) -> 1486428.4
A86: 2017 | B86: 37.432.689/0001-33 | C86: ABACO TECNOLOGIA DE INFORMACAO LTDA | D86: ABACO TECNOLOGIA DE INFORMACAO | E86: MATO GROSSO | F86: CUIABÁ | G86: 62023 - Desenvolvimento e licenciamento de programas de computador customizáveis | H86: Declarado pelo Contribuinte para Apuração do IRPJ e da CSLL | I86: Sudam/Sudene - Redução 75% Projeto Setor Prioritário | J86: 721975.39 | K86: =J86*_xlfn.XLOOKUP(A86,IPCA_Fatores!$A$2:$A$10,IPCA_Fatores!$C$2:$C$10) -> 1122070.5
A87: 2018 | B87: 37.432.689/0001-33 | C87: ABACO TECNOLOGIA DE INFORMACAO LTDA | D87: ABACO TECNOLOGIA DE INFORMACAO | E87: MATO GROSSO | F87: CUIABÁ | G87: 62023 - Desenvolvimento e licenciamento de programas de computador customizáveis | H87: Declarado pelo Contribuinte para Apuração do IRPJ e da CSLL | I87: Sudam/Sudene - Redução 75% Projeto Setor Prioritário | J87: 317242.66 | K87: =J87*_xlfn.XLOOKUP(A87,IPCA_Fatores!$A$2:$A$10,IPCA_Fatores!$C$2:$C$10) -> 475227.13
A88: 2019 | B88: 37.432.689/0001-33 | C88: ABACO TECNOLOGIA DE INFORMACAO LTDA | D88: ABACO TECNOLOGIA DE INFORMACAO | E88: MATO GROSSO | F88: CUIABÁ | G88: 62023 - Desenvolvimento e licenciamento de programas de computador customizáveis | H88: Declarado pelo Contribuinte para Apuração do IRPJ e da CSLL | I88: Sudam/Sudene - Redução 75% Projeto Setor Prioritário | J88: 177004.01 | K88: =J88*_xlfn.XLOOKUP(A88,IPCA_Fatores!$A$2:$A$10,IPCA_Fatores!$C$2:$C$10) -> 254194.88
A89: 2020 | B89: 37.432.689/0001-33 | C89: ABACO TECNOLOGIA DE INFORMACAO LTDA | D89: ABACO TECNOLOGIA DE INFORMACAO | E89: MATO GROSSO | F89: CUIABÁ | G89: 62023 - Desenvolvimento e licenciamento de programas de computador customizáveis | H89: Declarado pelo Contribuinte para Apuração do IRPJ e da CSLL | I89: Sudam/Sudene - Redução 75% Projeto Setor Prioritário | J89: 2045.9 | K89: =J89*_xlfn.XLOOKUP(A89,IPCA_Fatores!$A$2:$A$10,IPCA_Fatores!$C$2:$C$10) -> 2811.0508
A90: 2021 | B90: 37.432.689/0001-33 | C90: ABACO TECNOLOGIA DE INFORMACAO LTDA | D90: ABACO TECNOLOGIA DE INFORMACAO | E90: MATO GROSSO | F90: CUIABÁ | G90: 62023 - Desenvolvimento e licenciamento de programas de computador customizáveis | H90: Declarado pelo Contribuinte para Apuração do IRPJ e da CSLL | I90: Sudam/Sudene - Redução 75% Projeto Setor Prioritário | J90: 11864.67 | K90: =J90*_xlfn.XLOOKUP(A90,IPCA_Fatores!$A$2:$A$10,IPCA_Fatores!$C$2:$C$10) -> 14811.889
A91: 2022 | B91: 37.432.689/0001-33 | C91: ABACO TECNOLOGIA DE INFORMACAO LTDA | D91: ABACO TECNOLOGIA DE INFORMACAO | E91: MATO GROSSO | F91: CUIABÁ | G91: 62023 - Desenvolvimento e licenciamento de programas de computador customizáveis | H91: Declarado pelo Contribuinte para Apuração do IRPJ e da CSLL | I91: Sudam/Sudene - Redução 75% Projeto Setor Prioritário | J91: 42413.99 | K91: =J91*_xlfn.XLOOKUP(A91,IPCA_Fatores!$A$2:$A$10,IPCA_Fatores!$C$2:$C$10) -> 50051.754
A92: 2023 | B92: 37.432.689/0001-33 | C92: ABACO TECNOLOGIA DE INFORMACAO LTDA | D92: ABACO TECNOLOGIA DE INFORMACAO | E92: MATO GROSSO | F92: CUIABÁ | G92: 62023 - Desenvolvimento e licenciamento de programas de computador customizáveis | H92: Declarado pelo Contribuinte para Apuração do IRPJ e da CSLL | I92: Sudam/Sudene - Redução 75% Projeto Setor Prioritário | J92: 515275.18 | K92: =J92*_xlfn.XLOOKUP(A92,IPCA_Fatores!$A$2:$A$10,IPCA_Fatores!$C$2:$C$10) -> 581212.14
A93: 2015 | B93: 03.707.118/0001-42 | C93: ABATEDOURO SOLON LTDA | D93: FRANGO SOLON | E93: PARÁ | F93: BENEVIDES | G93: 10121 - Abate de suínos, aves e outros pequenos animais | H93: Declarado pelo Contribuinte para Apuração do IRPJ e da CSLL | I93: Sudam/Sudene - Redução 75% Projeto Setor Prioritário | J93: 1363944.2 | K93: =J93*_xlfn.XLOOKUP(A93,IPCA_Fatores!$A$2:$A$10,IPCA_Fatores!$C$2:$C$10) -> 2319600.1
A94: 2020 | B94: 03.707.118/0001-42 | C94: ABATEDOURO SOLON LTDA | D94: FRANGO SOLON | E94: PARÁ | F94: BENEVIDES | G94: 10121 - Abate de suínos, aves e outros pequenos animais | H94: Declarado pelo Contribuinte para Apuração do IRPJ e da CSLL | I94: Sudam/Sudene - Redução 75% Projeto Setor Prioritário | J94: 221946.53 | K94: =J94*_xlfn.XLOOKUP(A94,IPCA_Fatores!$A$2:$A$10,IPCA_Fatores!$C$2:$C$10) -> 304952.82
A95: 2021 | B95: 03.707.118/0001-42 | C95: ABATEDOURO SOLON LTDA | D95: FRANGO SOLON | E95: PARÁ | F95: BENEVIDES | G95: 10121 - Abate de suínos, aves e outros pequenos animais | H95: Declarado pelo Contribuinte para Apuração do IRPJ e da CSLL | I95: Sudam/Sudene - Redução 75% Projeto Setor Prioritário | J95: 2072022.5 | K95: =J95*_xlfn.XLOOKUP(A95,IPCA_Fatores!$A$2:$A$10,IPCA_Fatores!$C$2:$C$10) -> 2586719
... A108: 2020 | B108: 60.659.463/0029-92 | C108: ACHE LABORATORIOS FARMACEUTICOS SA | D108: ACHE - BIOSINTETICA - MELCON | E108: SÃO PAULO | F108: SÃO PAULO | G108: 00000 - Sem informação | H108: Declarado pelo Contribuinte para Apuração do IRPJ e da CSLL | I108: Sudam/Sudene - Redução 75% Projeto Setor Prioritário | J108: 18748391 | K108: =J108*_xlfn.XLOOKUP(A108,IPCA_Fatores!$A$2:$A$10,IPCA_Fatores!$C$2:$C$10) -> 25760144
A109: 2020 | B109: 60.659.463/0029-92 | C109: ACHE LABORATORIOS FARMACEUTICOS SA | D109: ACHE - BIOSINTETICA - MELCON | E109: SÃO PAULO | F109: SÃO PAULO | G109: 00000 - Sem informação | H109: Declarado pelo Contribuinte para Apuração do IRPJ e da CSLL | I109: Sudam/Sudene - Redução por Reinvestimento | J109: 18748391 | K109: =IFERROR(J109*VLOOKUP(A109,IPCA_Fatores!$A$2:$C$10,3,FALSE),J109) -> 25760144
A110: 2021 | B110: 60.659.463/0029-92 | C110: ACHE LABORATORIOS FARMACEUTICOS SA | D110: ACHE - BIOSINTETICA - MELCON | E110: SÃO PAULO | F110: SÃO PAULO | G110: 00000 - Sem informação | H110: Declarado pelo Contribuinte para Apuração do IRPJ e da CSLL | I110: Sudam/Sudene - Redução 75% Projeto Setor Prioritário | J110: 38121134 | K110: =J110*_xlfn.XLOOKUP(A110,IPCA_Fatores!$A$2:$A$10,IPCA_Fatores!$C$2:$C$10) -> 47590536
A111: 2022 | B111: 60.659.463/0029-92 | C111: ACHE LABORATORIOS FARMACEUTICOS SA | D111: ACHE - BIOSINTETICA - MELCON | E111: SÃO PAULO | F111: SÃO PAULO | G111: 00000 - Sem informação | H111: Declarado pelo Contribuinte para Apuração do IRPJ e da CSLL | I111: Sudam/Sudene - Redução 75% Projeto Setor Prioritário | J111: 43204467 | K111: =J111*_xlfn.XLOOKUP(A111,IPCA_Fatores!$A$2:$A$10,IPCA_Fatores!$C$2:$C$10) -> 50984577
A112: 2023 | B112: 60.659.463/0029-92 | C112: ACHE LABORATORIOS FARMACEUTICOS SA | D112: ACHE - BIOSINTETICA - MELCON | E112: SÃO PAULO | F112: SÃO PAULO | G112: 00000 - Sem informação | H112: Declarado pelo Contribuinte para Apuração do IRPJ e da CSLL | I112: Sudam/Sudene - Redução 75% Projeto Setor Prioritário | J112: 12044446 | K112: =J112*_xlfn.XLOOKUP(A112,IPCA_Fatores!$A$2:$A$10,IPCA_Fatores!$C$2:$C$10) -> 13585708
...

Sheet IPCA_Fatores
A1: Ano-Calendário | B1: Data-base | C1: Fator IPCA até 31/05/2026 | D1: Fonte/observação
A2: 2015 | B2: 31/12/2015 | C2: 1.7006561 | D2: Fator acumulado de jan do ano seguinte até mai/2026 (IPCA)
A3: 2016 | B3: 31/12/2016 | C3: 1.6000152 | D3: Fator acumulado de jan do ano seguinte até mai/2026 (IPCA)
A4: 2017 | B4: 31/12/2017 | C4: 1.5541672 | D4: Fator acumulado de jan do ano seguinte até mai/2026 (IPCA)
A5: 2018 | B5: 31/12/2018 | C5: 1.4979925 | D5: Fator acumulado de jan do ano seguinte até mai/2026 (IPCA)
A6: 2019 | B6: 31/12/2019 | C6: 1.4360968 | D6: Fator acumulado de jan do ano seguinte até mai/2026 (IPCA)
A7: 2020 | B7: 31/12/2020 | C7: 1.3739923 | D7: Fator acumulado de jan do ano seguinte até mai/2026 (IPCA)
A8: 2021 | B8: 31/12/2021 | C8: 1.248403 | D8: Fator acumulado de jan do ano seguinte até mai/2026 (IPCA)
A9: 2022 | B9: 31/12/2022 | C9: 1.1800765 | D9: Fator acumulado de jan do ano seguinte até mai/2026 (IPCA)
A10: 2023 | B10: 31/12/2023 | C10: 1.1279646 | D10: Fator acumulado de jan do ano seguinte até mai/2026 (IPCA)

Sheet Resumo_por_Empresa
A1: Nº | B1: Beneficiário | C1: Total Valor Renunciado (R$) | D1: Total Valor Atualizado IPCA (R$)
A2: =ROW()-1 -> 1 | B2: {=_xlfn._xlws.SORT(_xlfn.UNIQUE('Renúncias Fiscais Sudam-Sudene'!C2:C11311))} -> 1TELECOM SERVICOS DE TECNOLOGIA EM INTERNET LTDA | C2: =SUMIF('Renúncias Fiscais Sudam-Sudene'!C:C,B2,'Renúncias Fiscais Sudam-Sudene'!J:J) -> 4236763.1 | D2: =SUMIF('Renúncias Fiscais Sudam-Sudene'!C:C,B2,'Renúncias Fiscais Sudam-Sudene'!K:K) -> 5256781.8
A3: =ROW()-1 -> 2 | B3: 2 J COMERCIAL LTDA | C3: =SUMIF('Renúncias Fiscais Sudam-Sudene'!C:C,B3,'Renúncias Fiscais Sudam-Sudene'!J:J) -> 870884.36 | D3: =SUMIF('Renúncias Fiscais Sudam-Sudene'!C:C,B3,'Renúncias Fiscais Sudam-Sudene'!K:K) -> 982326.7
A4: =ROW()-1 -> 3 | B4: 3CAFFI INDUSTRIA E COMERCIO DE CAPSULAS S.A | C4: =SUMIF('Renúncias Fiscais Sudam-Sudene'!C:C,B4,'Renúncias Fiscais Sudam-Sudene'!J:J) -> 28230398 | D4: =SUMIF('Renúncias Fiscais Sudam-Sudene'!C:C,B4,'Renúncias Fiscais Sudam-Sudene'!K:K) -> 35206574
A5: =ROW()-1 -> 4 | B5: 3M MANAUS INDUSTRIA DE PRODUTOS QUIMICOS LTDA | C5: =SUMIF('Renúncias Fiscais Sudam-Sudene'!C:C,B5,'Renúncias Fiscais Sudam-Sudene'!J:J) -> 4.5758889e+08 | D5: =SUMIF('Renúncias Fiscais Sudam-Sudene'!C:C,B5,'Renúncias Fiscais Sudam-Sudene'!K:K) -> 6.1362146e+08
A6: =ROW()-1 -> 5 | B6: 3R BAHIA S.A | C6: =SUMIF('Renúncias Fiscais Sudam-Sudene'!C:C,B6,'Renúncias Fiscais Sudam-Sudene'!J:J) -> 821967.92 | D6: =SUMIF('Renúncias Fiscais Sudam-Sudene'!C:C,B6,'Renúncias Fiscais Sudam-Sudene'!K:K) -> 927150.69
A7: =ROW()-1 -> 6 | B7: 3R MACAU S.A. | C7: =SUMIF('Renúncias Fiscais Sudam-Sudene'!C:C,B7,'Renúncias Fiscais Sudam-Sudene'!J:J) -> 1.6969539e+08 | D7: =SUMIF('Renúncias Fiscais Sudam-Sudene'!C:C,B7,'Renúncias Fiscais Sudam-Sudene'!K:K) -> 1.961142e+08
A8: =ROW()-1 -> 7 | B8: 3R PETROLEUM OFFSHORE S.A. | C8: =SUMIF('Renúncias Fiscais Sudam-Sudene'!C:C,B8,'Renúncias Fiscais Sudam-Sudene'!J:J) -> 7294881.1 | D8: =SUMIF('Renúncias Fiscais Sudam-Sudene'!C:C,B8,'Renúncias Fiscais Sudam-Sudene'!K:K) -> 8228367.4
A9: =ROW()-1 -> 8 | B9: 3R POTIGUAR S.A. | C9: =SUMIF('Renúncias Fiscais Sudam-Sudene'!C:C,B9,'Renúncias Fiscais Sudam-Sudene'!J:J) -> 7504086.4 | D9: =SUMIF('Renúncias Fiscais Sudam-Sudene'!C:C,B9,'Renúncias Fiscais Sudam-Sudene'!K:K) -> 8464343.5
A10: =ROW()-1 -> 9 | B10: 3R RIO VENTURA S.A. | C10: =SUMIF('Renúncias Fiscais Sudam-Sudene'!C:C,B10,'Renúncias Fiscais Sudam-Sudene'!J:J) -> 22933753 | D10: =SUMIF('Renúncias Fiscais Sudam-Sudene'!C:C,B10,'Renúncias Fiscais Sudam-Sudene'!K:K) -> 26237968
A11: =ROW()-1 -> 10 | B11: 3R RNCE S.A. | C11: =SUMIF('Renúncias Fiscais Sudam-Sudene'!C:C,B11,'Renúncias Fiscais Sudam-Sudene'!J:J) -> 7517803.1 | D11: =SUMIF('Renúncias Fiscais Sudam-Sudene'!C:C,B11,'Renúncias Fiscais Sudam-Sudene'!K:K) -> 8676970.4
A12: =ROW()-1 -> 11 | B12: A ALVES DE SOUSA INDUSTRIA E COMERCIO DE MOTOS LTDA | C12: =SUMIF('Renúncias Fiscais Sudam-Sudene'!C:C,B12,'Renúncias Fiscais Sudam-Sudene'!J:J) -> 6289680.5 | D12: =SUMIF('Renúncias Fiscais Sudam-Sudene'!C:C,B12,'Renúncias Fiscais Sudam-Sudene'!K:K) -> 7663853.3
A13: =ROW()-1 -> 12 | B13: A G HOTEIS E TURISMO S/A | C13: =SUMIF('Renúncias Fiscais Sudam-Sudene'!C:C,B13,'Renúncias Fiscais Sudam-Sudene'!J:J) -> 7566596.7 | D13: =SUMIF('Renúncias Fiscais Sudam-Sudene'!C:C,B13,'Renúncias Fiscais Sudam-Sudene'!K:K) -> 10040665
A14: =ROW()-1 -> 13 | B14: A T S - TERCEIRIZACAO DE MAO DE OBRA LTDA | C14: =SUMIF('Renúncias Fiscais Sudam-Sudene'!C:C,B14,'Renúncias Fiscais Sudam-Sudene'!J:J) -> 673582.76 | D14: =SUMIF('Renúncias Fiscais Sudam-Sudene'!C:C,B14,'Renúncias Fiscais Sudam-Sudene'!K:K) -> 759777.49
... A2248: =ROW()-1 -> 2247 | B2248: ZTT DO BRASIL LTDA | C2248: =SUMIF('Renúncias Fiscais Sudam-Sudene'!C:C,B2248,'Renúncias Fiscais Sudam-Sudene'!J:J) -> 3518118.7 | D2248: =SUMIF('Renúncias Fiscais Sudam-Sudene'!C:C,B2248,'Renúncias Fiscais Sudam-Sudene'!K:K) -> 4810114
B2249: TOTAL GERAL | C2249: =SUM(C2:C2248) -> 1.2648412e+11 | D2249: =SUM(D2:D2248) -> 1.6624748e+11
